{
  "health_percentage": 42,
  "description": "A bazel toolchain for using prebuilt binaries for buildifier and buildozer",
  "documentation": null,
  "files": {
    "code_of_conduct": null,
    "code_of_conduct_file": null,
    "contributing": null,
    "issue_template": null,
    "pull_request_template": null,
    "license": {
      "key": "mit",
      "name": "MIT License",
      "spdx_id": "MIT",
      "url": "https://api.github.com/licenses/mit",
      "node_id": "MDc6TGljZW5zZTEz",
      "html_url": "https://github.com/keith/buildifier-prebuilt/blob/main/LICENSE"
    },
    "readme": {
      "url": "https://api.github.com/repos/keith/buildifier-prebuilt/contents/README.md",
      "html_url": "https://github.com/keith/buildifier-prebuilt/blob/main/README.md"
    }
  },
  "updated_at": null
}
